lubar/__init__.py
lubar/progressbar.py
lubar-0.0.4.dist-info/LICENSE
lubar-0.0.4.dist-info/METADATA
lubar-0.0.4.dist-info/WHEEL
lubar-0.0.4.dist-info/top_level.txt
lubar-0.0.4.dist-info/RECORD
