Metadata-Version: 2.1
Name: lubar
Version: 0.0.4
Summary: Pythonic progress bar
Home-page: https://github.com/dariush-bahrami/lubar
Author: Dariush Bahrami
Author-email: dariushbahrami1993@gmail.com
License: UNKNOWN
Project-URL: Bug Tracker, https://github.com/dariush-bahrami/lubar/issues
Platform: UNKNOWN
Classifier: Programming Language :: Python :: 3
Classifier: License :: OSI Approved :: GNU General Public License v3 (GPLv3)
Classifier: Operating System :: OS Independent
Requires-Python: >=3.6
License-File: LICENSE
